shmapy/__init__.py
shmapy/__main__.py
shmapy/facet_shmap.py
shmapy/hex_shmap.py
shmapy/input.py
shmapy/static/demo_input1.csv
shmapy/static/demo_input2.csv
shmapy/static/demo_input3.csv
shmapy/static/demo_input4.csv
shmapy/static/demo_input5.csv
shmapy/static/demo_input6.csv
shmapy/static/facet_geo_states.csv
shmapy/static/state_coordinates.csv
shmapy-0.3.data/scripts/__init__.py
shmapy-0.3.data/scripts/__main__.py
shmapy-0.3.data/scripts/facet_shmap.py
shmapy-0.3.data/scripts/hex_shmap.py
shmapy-0.3.data/scripts/input.py
tests/__init__.py
tests/test_facet_shmap.py
tests/test_hex_shmap.py
tests/test_input.py
shmapy-0.3.dist-info/LICENSE
shmapy-0.3.dist-info/METADATA
shmapy-0.3.dist-info/WHEEL
shmapy-0.3.dist-info/entry_points.txt
shmapy-0.3.dist-info/top_level.txt
shmapy-0.3.dist-info/RECORD
