Metadata-Version: 2.1
Name: shmapy
Version: 0.3
Summary: The most amazing package for building hex maps
Home-page: UNKNOWN
Author: UNKNOWN
Author-email: UNKNOWN
License: BSD 3-Clause License
Keywords: map,hexagons,united_states
Platform: UNKNOWN
Classifier: License :: OSI Approved :: BSD License
Classifier: Programming Language :: Python :: 3
Classifier: Programming Language :: Python :: 3.8
Requires-Dist: fire
Requires-Dist: matplotlib
Requires-Dist: pandas
Requires-Dist: logzero
